[
  {
    "date": "20260326",
    "nav": 1.088,
    "change": -2.2462
  },
  {
    "date": "20260325",
    "nav": 1.113,
    "change": 2.9602
  },
  {
    "date": "20260324",
    "nav": 1.081,
    "change": 1.4071
  },
  {
    "date": "20260323",
    "nav": 1.066,
    "change": -4.9911
  },
  {
    "date": "20260320",
    "nav": 1.122,
    "change": -1.2324
  },
  {
    "date": "20260319",
    "nav": 1.136,
    "change": -1.9845
  },
  {
    "date": "20260318",
    "nav": 1.159,
    "change": 1.5776
  },
  {
    "date": "20260317",
    "nav": 1.141,
    "change": -2.8936
  },
  {
    "date": "20260316",
    "nav": 1.175,
    "change": 2.0851
  },
  {
    "date": "20260313",
    "nav": 1.151,
    "change": -0.7759
  },
  {
    "date": "20260312",
    "nav": 1.16,
    "change": -1.0239
  },
  {
    "date": "20260311",
    "nav": 1.172,
    "change": -0.1704
  },
  {
    "date": "20260310",
    "nav": 1.174,
    "change": 3.5273
  },
  {
    "date": "20260309",
    "nav": 1.134,
    "change": -1.6479
  },
  {
    "date": "20260306",
    "nav": 1.153,
    "change": 0.0868
  },
  {
    "date": "20260305",
    "nav": 1.152,
    "change": 1.677
  },
  {
    "date": "20260304",
    "nav": 1.133,
    "change": -0.0882
  },
  {
    "date": "20260303",
    "nav": 1.134,
    "change": -4.223
  },
  {
    "date": "20260302",
    "nav": 1.184,
    "change": -1.6611
  },
  {
    "date": "20260227",
    "nav": 1.204,
    "change": -0.6601
  },
  {
    "date": "20260226",
    "nav": 1.212,
    "change": 1.5926
  },
  {
    "date": "20260225",
    "nav": 1.193,
    "change": 1.1017
  },
  {
    "date": "20260224",
    "nav": 1.18,
    "change": 1.9879
  },
  {
    "date": "20260213",
    "nav": 1.157,
    "change": -0.4303
  },
  {
    "date": "20260212",
    "nav": 1.162,
    "change": 1.8405
  },
  {
    "date": "20260211",
    "nav": 1.141,
    "change": -1.2121
  },
  {
    "date": "20260210",
    "nav": 1.155,
    "change": 0.0
  },
  {
    "date": "20260209",
    "nav": 1.155,
    "change": 2.4845
  },
  {
    "date": "20260206",
    "nav": 1.127,
    "change": -0.4417
  },
  {
    "date": "20260205",
    "nav": 1.132,
    "change": -0.8757
  }
]